[
  {
    "ContainingType": "project1.Program\u002B\u003C\u003Ec",
    "Method": "\u003CMain\u003Eb__0_4",
    "RelativePath": "",
    "HttpMethod": "GET",
    "IsController": false,
    "Order": 0,
    "Parameters": [],
    "ReturnTypes": [
      {
        "Type": "System.Void",
        "MediaTypes": [],
        "StatusCode": 200
      }
    ]
  },
  {
    "ContainingType": "project1.Controllers.Admin.CoursesController",
    "Method": "Get",
    "RelativePath": "api/admin/Courses",
    "HttpMethod": "GET",
    "IsController": true,
    "Order": 0,
    "Parameters": [
      {
        "Name": "page",
        "Type": "System.Int32",
        "IsRequired": false
      },
      {
        "Name": "pageSize",
        "Type": "System.Int32",
        "IsRequired": false
      },
      {
        "Name": "filter",
        "Type": "System.String",
        "IsRequired": false
      },
      {
        "Name": "departmentId",
        "Type": "System.Nullable\u00601[[System.Guid, System.Private.CoreLib, Version=9.0.0.0, Culture=neutral, PublicKeyToken=7cec85d7bea7798e]]",
        "IsRequired": false
      }
    ],
    "ReturnTypes": []
  },
  {
    "ContainingType": "project1.Controllers.Admin.CoursesController",
    "Method": "Create",
    "RelativePath": "api/admin/Courses",
    "HttpMethod": "POST",
    "IsController": true,
    "Order": 0,
    "Parameters": [
      {
        "Name": "request",
        "Type": "project1.Application.DTOs.Admin.CreateCourseRequest",
        "IsRequired": true
      }
    ],
    "ReturnTypes": []
  },
  {
    "ContainingType": "project1.Controllers.Admin.CoursesController",
    "Method": "GetById",
    "RelativePath": "api/admin/Courses/{id}",
    "HttpMethod": "GET",
    "IsController": true,
    "Order": 0,
    "Parameters": [
      {
        "Name": "id",
        "Type": "System.Guid",
        "IsRequired": true
      }
    ],
    "ReturnTypes": []
  },
  {
    "ContainingType": "project1.Controllers.Admin.CoursesController",
    "Method": "Update",
    "RelativePath": "api/admin/Courses/{id}",
    "HttpMethod": "PUT",
    "IsController": true,
    "Order": 0,
    "Parameters": [
      {
        "Name": "id",
        "Type": "System.Guid",
        "IsRequired": true
      },
      {
        "Name": "request",
        "Type": "project1.Application.DTOs.Admin.CreateCourseRequest",
        "IsRequired": true
      }
    ],
    "ReturnTypes": []
  },
  {
    "ContainingType": "project1.Controllers.Admin.CoursesController",
    "Method": "Delete",
    "RelativePath": "api/admin/Courses/{id}",
    "HttpMethod": "DELETE",
    "IsController": true,
    "Order": 0,
    "Parameters": [
      {
        "Name": "id",
        "Type": "System.Guid",
        "IsRequired": true
      }
    ],
    "ReturnTypes": []
  },
  {
    "ContainingType": "project1.Controllers.Admin.DepartmentsController",
    "Method": "Get",
    "RelativePath": "api/admin/Departments",
    "HttpMethod": "GET",
    "IsController": true,
    "Order": 0,
    "Parameters": [
      {
        "Name": "page",
        "Type": "System.Int32",
        "IsRequired": false
      },
      {
        "Name": "pageSize",
        "Type": "System.Int32",
        "IsRequired": false
      },
      {
        "Name": "filter",
        "Type": "System.String",
        "IsRequired": false
      }
    ],
    "ReturnTypes": []
  },
  {
    "ContainingType": "project1.Controllers.Admin.DepartmentsController",
    "Method": "Create",
    "RelativePath": "api/admin/Departments",
    "HttpMethod": "POST",
    "IsController": true,
    "Order": 0,
    "Parameters": [
      {
        "Name": "request",
        "Type": "project1.Application.DTOs.Admin.CreateDepartmentRequest",
        "IsRequired": true
      }
    ],
    "ReturnTypes": []
  },
  {
    "ContainingType": "project1.Controllers.Admin.DepartmentsController",
    "Method": "GetById",
    "RelativePath": "api/admin/Departments/{id}",
    "HttpMethod": "GET",
    "IsController": true,
    "Order": 0,
    "Parameters": [
      {
        "Name": "id",
        "Type": "System.Guid",
        "IsRequired": true
      }
    ],
    "ReturnTypes": []
  },
  {
    "ContainingType": "project1.Controllers.Admin.DepartmentsController",
    "Method": "Update",
    "RelativePath": "api/admin/Departments/{id}",
    "HttpMethod": "PUT",
    "IsController": true,
    "Order": 0,
    "Parameters": [
      {
        "Name": "id",
        "Type": "System.Guid",
        "IsRequired": true
      },
      {
        "Name": "request",
        "Type": "project1.Application.DTOs.Admin.CreateDepartmentRequest",
        "IsRequired": true
      }
    ],
    "ReturnTypes": []
  },
  {
    "ContainingType": "project1.Controllers.Admin.DepartmentsController",
    "Method": "Delete",
    "RelativePath": "api/admin/Departments/{id}",
    "HttpMethod": "DELETE",
    "IsController": true,
    "Order": 0,
    "Parameters": [
      {
        "Name": "id",
        "Type": "System.Guid",
        "IsRequired": true
      }
    ],
    "ReturnTypes": []
  },
  {
    "ContainingType": "project1.Controllers.Admin.UsersController",
    "Method": "Get",
    "RelativePath": "api/admin/Users",
    "HttpMethod": "GET",
    "IsController": true,
    "Order": 0,
    "Parameters": [
      {
        "Name": "page",
        "Type": "System.Int32",
        "IsRequired": false
      },
      {
        "Name": "pageSize",
        "Type": "System.Int32",
        "IsRequired": false
      },
      {
        "Name": "filter",
        "Type": "System.String",
        "IsRequired": false
      }
    ],
    "ReturnTypes": []
  },
  {
    "ContainingType": "project1.Controllers.Admin.UsersController",
    "Method": "Create",
    "RelativePath": "api/admin/Users",
    "HttpMethod": "POST",
    "IsController": true,
    "Order": 0,
    "Parameters": [
      {
        "Name": "request",
        "Type": "project1.Application.DTOs.Admin.CreateUserRequest",
        "IsRequired": true
      }
    ],
    "ReturnTypes": []
  },
  {
    "ContainingType": "project1.Controllers.Admin.UsersController",
    "Method": "GetById",
    "RelativePath": "api/admin/Users/{id}",
    "HttpMethod": "GET",
    "IsController": true,
    "Order": 0,
    "Parameters": [
      {
        "Name": "id",
        "Type": "System.Guid",
        "IsRequired": true
      }
    ],
    "ReturnTypes": []
  },
  {
    "ContainingType": "project1.Controllers.Admin.UsersController",
    "Method": "Update",
    "RelativePath": "api/admin/Users/{id}",
    "HttpMethod": "PUT",
    "IsController": true,
    "Order": 0,
    "Parameters": [
      {
        "Name": "id",
        "Type": "System.Guid",
        "IsRequired": true
      },
      {
        "Name": "request",
        "Type": "project1.Application.DTOs.Admin.CreateUserRequest",
        "IsRequired": true
      }
    ],
    "ReturnTypes": []
  },
  {
    "ContainingType": "project1.Controllers.Admin.UsersController",
    "Method": "Delete",
    "RelativePath": "api/admin/Users/{id}",
    "HttpMethod": "DELETE",
    "IsController": true,
    "Order": 0,
    "Parameters": [
      {
        "Name": "id",
        "Type": "System.Guid",
        "IsRequired": true
      }
    ],
    "ReturnTypes": []
  },
  {
    "ContainingType": "project1.Controllers.AuthController",
    "Method": "Login",
    "RelativePath": "api/Auth/login",
    "HttpMethod": "POST",
    "IsController": true,
    "Order": 0,
    "Parameters": [
      {
        "Name": "request",
        "Type": "project1.Application.DTOs.Auth.LoginRequest",
        "IsRequired": true
      }
    ],
    "ReturnTypes": []
  },
  {
    "ContainingType": "project1.Controllers.AuthController",
    "Method": "LogoutAll",
    "RelativePath": "api/Auth/logout-all",
    "HttpMethod": "POST",
    "IsController": true,
    "Order": 0,
    "Parameters": [],
    "ReturnTypes": []
  },
  {
    "ContainingType": "project1.Controllers.AuthController",
    "Method": "Refresh",
    "RelativePath": "api/Auth/refresh-token",
    "HttpMethod": "POST",
    "IsController": true,
    "Order": 0,
    "Parameters": [
      {
        "Name": "token",
        "Type": "System.String",
        "IsRequired": true
      }
    ],
    "ReturnTypes": []
  },
  {
    "ContainingType": "project1.Controllers.AuthController",
    "Method": "Register",
    "RelativePath": "api/Auth/register",
    "HttpMethod": "POST",
    "IsController": true,
    "Order": 0,
    "Parameters": [
      {
        "Name": "request",
        "Type": "project1.Application.DTOs.Auth.RegisterRequest",
        "IsRequired": true
      }
    ],
    "ReturnTypes": []
  },
  {
    "ContainingType": "project1.Controllers.AuthController",
    "Method": "Revoke",
    "RelativePath": "api/Auth/revoke-token",
    "HttpMethod": "POST",
    "IsController": true,
    "Order": 0,
    "Parameters": [
      {
        "Name": "token",
        "Type": "System.String",
        "IsRequired": true
      }
    ],
    "ReturnTypes": []
  },
  {
    "ContainingType": "project1.Controllers.Student.StudentNotificationsController",
    "Method": "GetNotifications",
    "RelativePath": "api/student/notifications",
    "HttpMethod": "GET",
    "IsController": true,
    "Order": 0,
    "Parameters": [
      {
        "Name": "unreadOnly",
        "Type": "System.Boolean",
        "IsRequired": false
      }
    ],
    "ReturnTypes": []
  },
  {
    "ContainingType": "project1.Controllers.Student.StudentNotificationsController",
    "Method": "MarkAsRead",
    "RelativePath": "api/student/notifications/{id}/read",
    "HttpMethod": "POST",
    "IsController": true,
    "Order": 0,
    "Parameters": [
      {
        "Name": "id",
        "Type": "System.Guid",
        "IsRequired": true
      }
    ],
    "ReturnTypes": []
  },
  {
    "ContainingType": "project1.Controllers.Student.StudentNotificationsController",
    "Method": "MarkAllAsRead",
    "RelativePath": "api/student/notifications/read-all",
    "HttpMethod": "POST",
    "IsController": true,
    "Order": 0,
    "Parameters": [],
    "ReturnTypes": []
  },
  {
    "ContainingType": "project1.Controllers.Student.StudentNotificationsController",
    "Method": "GetUnreadCount",
    "RelativePath": "api/student/notifications/unread-count",
    "HttpMethod": "GET",
    "IsController": true,
    "Order": 0,
    "Parameters": [],
    "ReturnTypes": []
  },
  {
    "ContainingType": "project1.Controllers.Student.StudentController",
    "Method": "GetAttendance",
    "RelativePath": "api/student/Student/attendance",
    "HttpMethod": "GET",
    "IsController": true,
    "Order": 0,
    "Parameters": [
      {
        "Name": "classId",
        "Type": "System.Nullable\u00601[[System.Guid, System.Private.CoreLib, Version=9.0.0.0, Culture=neutral, PublicKeyToken=7cec85d7bea7798e]]",
        "IsRequired": false
      },
      {
        "Name": "from",
        "Type": "System.Nullable\u00601[[System.DateTime, System.Private.CoreLib, Version=9.0.0.0, Culture=neutral, PublicKeyToken=7cec85d7bea7798e]]",
        "IsRequired": false
      },
      {
        "Name": "to",
        "Type": "System.Nullable\u00601[[System.DateTime, System.Private.CoreLib, Version=9.0.0.0, Culture=neutral, PublicKeyToken=7cec85d7bea7798e]]",
        "IsRequired": false
      }
    ],
    "ReturnTypes": []
  },
  {
    "ContainingType": "project1.Controllers.Student.StudentController",
    "Method": "GetClasses",
    "RelativePath": "api/student/Student/classes",
    "HttpMethod": "GET",
    "IsController": true,
    "Order": 0,
    "Parameters": [
      {
        "Name": "page",
        "Type": "System.Int32",
        "IsRequired": false
      },
      {
        "Name": "pageSize",
        "Type": "System.Int32",
        "IsRequired": false
      }
    ],
    "ReturnTypes": []
  },
  {
    "ContainingType": "project1.Controllers.Student.StudentController",
    "Method": "GetGrades",
    "RelativePath": "api/student/Student/grades",
    "HttpMethod": "GET",
    "IsController": true,
    "Order": 0,
    "Parameters": [
      {
        "Name": "assignmentId",
        "Type": "System.Nullable\u00601[[System.Guid, System.Private.CoreLib, Version=9.0.0.0, Culture=neutral, PublicKeyToken=7cec85d7bea7798e]]",
        "IsRequired": false
      }
    ],
    "ReturnTypes": []
  },
  {
    "ContainingType": "project1.Controllers.Student.SubmissionsController",
    "Method": "Submit",
    "RelativePath": "api/student/Submissions/{assignmentId}/submit",
    "HttpMethod": "POST",
    "IsController": true,
    "Order": 0,
    "Parameters": [
      {
        "Name": "assignmentId",
        "Type": "System.Guid",
        "IsRequired": true
      },
      {
        "Name": "File",
        "Type": "Microsoft.AspNetCore.Http.IFormFile",
        "IsRequired": false
      },
      {
        "Name": "FileUrl",
        "Type": "System.String",
        "IsRequired": false
      }
    ],
    "ReturnTypes": []
  },
  {
    "ContainingType": "project1.Controllers.Student.SubmissionsController",
    "Method": "GetForAssignment",
    "RelativePath": "api/student/Submissions/assignment/{assignmentId}",
    "HttpMethod": "GET",
    "IsController": true,
    "Order": 0,
    "Parameters": [
      {
        "Name": "assignmentId",
        "Type": "System.Guid",
        "IsRequired": true
      }
    ],
    "ReturnTypes": []
  },
  {
    "ContainingType": "project1.Controllers.Teacher.AssignmentsController",
    "Method": "Create",
    "RelativePath": "api/teacher/Assignments",
    "HttpMethod": "POST",
    "IsController": true,
    "Order": 0,
    "Parameters": [
      {
        "Name": "request",
        "Type": "project1.Application.DTOs.Teacher.CreateAssignmentRequest",
        "IsRequired": true
      }
    ],
    "ReturnTypes": []
  },
  {
    "ContainingType": "project1.Controllers.Teacher.AssignmentsController",
    "Method": "GetForClass",
    "RelativePath": "api/teacher/Assignments/class/{classId}",
    "HttpMethod": "GET",
    "IsController": true,
    "Order": 0,
    "Parameters": [
      {
        "Name": "classId",
        "Type": "System.Guid",
        "IsRequired": true
      },
      {
        "Name": "page",
        "Type": "System.Int32",
        "IsRequired": false
      },
      {
        "Name": "pageSize",
        "Type": "System.Int32",
        "IsRequired": false
      }
    ],
    "ReturnTypes": []
  },
  {
    "ContainingType": "project1.Controllers.Teacher.AssignmentsController",
    "Method": "Grade",
    "RelativePath": "api/teacher/Assignments/submissions/{submissionId}/grade",
    "HttpMethod": "POST",
    "IsController": true,
    "Order": 0,
    "Parameters": [
      {
        "Name": "submissionId",
        "Type": "System.Guid",
        "IsRequired": true
      },
      {
        "Name": "model",
        "Type": "project1.Controllers.Teacher.GradeRequest",
        "IsRequired": true
      }
    ],
    "ReturnTypes": []
  },
  {
    "ContainingType": "project1.Controllers.Teacher.AttendanceController",
    "Method": "Mark",
    "RelativePath": "api/teacher/Attendance",
    "HttpMethod": "POST",
    "IsController": true,
    "Order": 0,
    "Parameters": [
      {
        "Name": "request",
        "Type": "project1.Application.DTOs.Teacher.AttendanceMarkRequest",
        "IsRequired": true
      }
    ],
    "ReturnTypes": []
  },
  {
    "ContainingType": "project1.Controllers.Teacher.ClassesController",
    "Method": "Get",
    "RelativePath": "api/teacher/Classes",
    "HttpMethod": "GET",
    "IsController": true,
    "Order": 0,
    "Parameters": [
      {
        "Name": "page",
        "Type": "System.Int32",
        "IsRequired": false
      },
      {
        "Name": "pageSize",
        "Type": "System.Int32",
        "IsRequired": false
      }
    ],
    "ReturnTypes": []
  },
  {
    "ContainingType": "project1.Controllers.Teacher.ClassesController",
    "Method": "Create",
    "RelativePath": "api/teacher/Classes",
    "HttpMethod": "POST",
    "IsController": true,
    "Order": 0,
    "Parameters": [
      {
        "Name": "request",
        "Type": "project1.Application.DTOs.Teacher.CreateClassRequest",
        "IsRequired": true
      }
    ],
    "ReturnTypes": []
  },
  {
    "ContainingType": "project1.Controllers.Teacher.ClassesController",
    "Method": "GetById",
    "RelativePath": "api/teacher/Classes/{id}",
    "HttpMethod": "GET",
    "IsController": true,
    "Order": 0,
    "Parameters": [
      {
        "Name": "id",
        "Type": "System.Guid",
        "IsRequired": true
      }
    ],
    "ReturnTypes": []
  },
  {
    "ContainingType": "project1.Controllers.Teacher.ClassesController",
    "Method": "Update",
    "RelativePath": "api/teacher/Classes/{id}",
    "HttpMethod": "PUT",
    "IsController": true,
    "Order": 0,
    "Parameters": [
      {
        "Name": "id",
        "Type": "System.Guid",
        "IsRequired": true
      },
      {
        "Name": "request",
        "Type": "project1.Application.DTOs.Teacher.CreateClassRequest",
        "IsRequired": true
      }
    ],
    "ReturnTypes": []
  },
  {
    "ContainingType": "project1.Controllers.Teacher.ClassesController",
    "Method": "AssignStudents",
    "RelativePath": "api/teacher/Classes/{id}/students",
    "HttpMethod": "POST",
    "IsController": true,
    "Order": 0,
    "Parameters": [
      {
        "Name": "id",
        "Type": "System.Guid",
        "IsRequired": true
      },
      {
        "Name": "studentIds",
        "Type": "System.Guid[]",
        "IsRequired": true
      }
    ],
    "ReturnTypes": []
  },
  {
    "ContainingType": "project1.Controllers.Teacher.TeacherNotificationsController",
    "Method": "CreateNotification",
    "RelativePath": "api/teacher/notifications",
    "HttpMethod": "POST",
    "IsController": true,
    "Order": 0,
    "Parameters": [
      {
        "Name": "request",
        "Type": "project1.Application.DTOs.Notifications.CreateNotificationRequest",
        "IsRequired": true
      }
    ],
    "ReturnTypes": []
  },
  {
    "ContainingType": "project1.Controllers.Teacher.TeacherNotificationsController",
    "Method": "GetMyNotifications",
    "RelativePath": "api/teacher/notifications",
    "HttpMethod": "GET",
    "IsController": true,
    "Order": 0,
    "Parameters": [
      {
        "Name": "unreadOnly",
        "Type": "System.Boolean",
        "IsRequired": false
      }
    ],
    "ReturnTypes": []
  },
  {
    "ContainingType": "project1.Controllers.Teacher.TeacherNotificationsController",
    "Method": "MarkAsRead",
    "RelativePath": "api/teacher/notifications/{id}/read",
    "HttpMethod": "POST",
    "IsController": true,
    "Order": 0,
    "Parameters": [
      {
        "Name": "id",
        "Type": "System.Guid",
        "IsRequired": true
      }
    ],
    "ReturnTypes": []
  },
  {
    "ContainingType": "project1.Controllers.Teacher.TeacherNotificationsController",
    "Method": "MarkAllAsRead",
    "RelativePath": "api/teacher/notifications/read-all",
    "HttpMethod": "POST",
    "IsController": true,
    "Order": 0,
    "Parameters": [],
    "ReturnTypes": []
  },
  {
    "ContainingType": "project1.Controllers.Teacher.TeacherNotificationsController",
    "Method": "GetUnreadCount",
    "RelativePath": "api/teacher/notifications/unread-count",
    "HttpMethod": "GET",
    "IsController": true,
    "Order": 0,
    "Parameters": [],
    "ReturnTypes": []
  },
  {
    "ContainingType": "project1.Controllers.WeatherForecastController",
    "Method": "Get",
    "RelativePath": "WeatherForecast",
    "HttpMethod": "GET",
    "IsController": true,
    "Order": 0,
    "Parameters": [],
    "ReturnTypes": [
      {
        "Type": "System.Collections.Generic.IEnumerable\u00601[[project1.WeatherForecast, project1, Version=1.0.0.0, Culture=neutral, PublicKeyToken=null]]",
        "MediaTypes": [
          "text/plain",
          "application/json",
          "text/json"
        ],
        "StatusCode": 200
      }
    ],
    "EndpointName": "GetWeatherForecast"
  }
]